pyworld3/__init__.py
pyworld3/agriculture.py
pyworld3/capital.py
pyworld3/functions_table_world3.json
pyworld3/pollution.py
pyworld3/population.py
pyworld3/resource.py
pyworld3/specials.py
pyworld3/test_sectors.py
pyworld3/utils.py
pyworld3/world3.py
pyworld3-1.1.dist-info/LICENSE
pyworld3-1.1.dist-info/METADATA
pyworld3-1.1.dist-info/WHEEL
pyworld3-1.1.dist-info/top_level.txt
pyworld3-1.1.dist-info/RECORD
