Metadata-Version: 2.1
Name: pyworld3
Version: 1.1
Summary: The World3 model revisited in Python.
Home-page: http://github.com/cvanwynsberghe/pyworld3
Author: Charles Vanwynsberghe
Author-email: UNKNOWN
License: CeCILL
Download-URL: https://github.com/cvanwynsberghe/pyworld3/archive/v1.1.tar.gz
Platform: UNKNOWN
Classifier: Programming Language :: Python
Classifier: Natural Language :: English
Classifier: Operating System :: OS Independent
Classifier: Topic :: Scientific/Engineering
Classifier: Topic :: Education
Classifier: Intended Audience :: Science/Research
Classifier: Intended Audience :: Education
Classifier: License :: OSI Approved :: CEA CNRS Inria Logiciel Libre License, version 2.1 (CeCILL-2.1)
Requires-Dist: numpy
Requires-Dist: scipy
Requires-Dist: matplotlib
